quanstants/__init__.py
quanstants/abstract_quantity.py
quanstants/abstract_unit.py
quanstants/config.py
quanstants/config.toml
quanstants/constant.py
quanstants/dimensions.py
quanstants/exceptions.py
quanstants/format.py
quanstants/log.py
quanstants/prefix.py
quanstants/quantity.py
quanstants/rounding.py
quanstants/temperature.py
quanstants/uncertainties.py
quanstants/unicode.py
quanstants/unit.py
quanstants/constants/__init__.py
quanstants/constants/codata2018.py
quanstants/constants/fundamental.py
quanstants/interfaces/__init__.py
quanstants/interfaces/astropy.py
quanstants/interfaces/matplotlib.py
quanstants/interfaces/pandas.py
quanstants/interfaces/pint.py
quanstants/interfaces/polars.py
quanstants/prefixes/__init__.py
quanstants/prefixes/binary.py
quanstants/prefixes/metric.py
quanstants/units/__init__.py
quanstants/units/astronomy.py
quanstants/units/atomic.py
quanstants/units/base.py
quanstants/units/chemistry.py
quanstants/units/common.py
quanstants/units/computing.py
quanstants/units/imperial.py
quanstants/units/logarithmic.py
quanstants/units/natural.py
quanstants/units/partsper.py
quanstants/units/planck.py
quanstants/units/prefixed.py
quanstants/units/si.py
quanstants/units/temperatures.py
quanstants/units/us.py
quanstants-0.1.0.dist-info/METADATA
quanstants-0.1.0.dist-info/WHEEL
quanstants-0.1.0.dist-info/licenses/LICENSE
quanstants-0.1.0.dist-info/RECORD
