Metadata-Version: 2.3
Name: quanstants
Version: 0.1.0
Summary: Intuitive and unastonishing physical quantities, units, constants, and uncertainties in Python
Project-URL: Homepage, https://github.com/matterhorn103/quanstants
Project-URL: Issues, https://github.com/matterhorn103/quanstants/issues
Author-email: "Matthew J. Milner" <matterhorn103@proton.me>
License-File: LICENSE
Classifier: License :: OSI Approved :: MIT License
Classifier: Operating System :: OS Independent
Classifier: Programming Language :: Python :: 3
Classifier: Topic :: Scientific/Engineering
Requires-Python: >=3.11
Requires-Dist: platformdirs>=4.2.1
Requires-Dist: tomli-w>=1.0.0
